eth_abi/__init__.py
ethereum_abi_utils-0.4.7.dist-info/DESCRIPTION.rst
ethereum_abi_utils-0.4.7.dist-info/METADATA
ethereum_abi_utils-0.4.7.dist-info/RECORD
ethereum_abi_utils-0.4.7.dist-info/WHEEL
ethereum_abi_utils-0.4.7.dist-info/metadata.json
ethereum_abi_utils-0.4.7.dist-info/top_level.txt
